mypy_strict_kwargs/__init__.py
mypy_strict_kwargs/plugin.py
mypy_strict_kwargs/py.typed
mypy_strict_kwargs-2025.4.3.dist-info/licenses/LICENSE
mypy_strict_kwargs-2025.4.3.dist-info/METADATA
mypy_strict_kwargs-2025.4.3.dist-info/WHEEL
mypy_strict_kwargs-2025.4.3.dist-info/entry_points.txt
mypy_strict_kwargs-2025.4.3.dist-info/top_level.txt
mypy_strict_kwargs-2025.4.3.dist-info/RECORD
