Metadata-Version: 2.4
Name: mypy-strict-kwargs
Version: 2025.4.3
Summary: Enforce using keyword arguments where possible.
Author-email: Adam Dangoor <adamdangoor@gmail.com>
License: MIT License
Project-URL: Documentation, https://mypy-strict-kwargs.readthedocs.io/en/latest/
Project-URL: Source, https://github.com/adamtheturtle/mypy-strict-kwargs
Keywords: mypy
Classifier: Development Status :: 5 - Production/Stable
Classifier: Environment :: Web Environment
Classifier: License :: OSI Approved :: MIT License
Classifier: Operating System :: Microsoft :: Windows
Classifier: Operating System :: POSIX
Classifier: Programming Language :: Python :: 3 :: Only
Classifier: Programming Language :: Python :: 3.10
Classifier: Programming Language :: Python :: 3.11
Classifier: Programming Language :: Python :: 3.12
Classifier: Programming Language :: Python :: 3.13
Requires-Python: >=3.10
License-File: LICENSE
Requires-Dist: mypy>=1.13.0
Requires-Dist: tomli>=1.2.2
Provides-Extra: dev
Requires-Dist: actionlint-py==1.7.7.23; extra == "dev"
Requires-Dist: check-manifest==0.50; extra == "dev"
Requires-Dist: deptry==0.23.0; extra == "dev"
Requires-Dist: doc8==1.1.2; extra == "dev"
Requires-Dist: doccmd==2025.2.18; extra == "dev"
Requires-Dist: docformatter==1.7.5; extra == "dev"
Requires-Dist: interrogate==1.7.0; extra == "dev"
Requires-Dist: mypy[faster-cache]==1.15.0; extra == "dev"
Requires-Dist: pre-commit==4.2.0; extra == "dev"
Requires-Dist: pyenchant==3.3.0rc1; extra == "dev"
Requires-Dist: pylint==3.3.6; extra == "dev"
Requires-Dist: pylint-per-file-ignores==1.4.0; extra == "dev"
Requires-Dist: pyproject-fmt==2.5.1; extra == "dev"
Requires-Dist: pyright==1.1.398; extra == "dev"
Requires-Dist: pyroma==4.2; extra == "dev"
Requires-Dist: pytest==8.3.5; extra == "dev"
Requires-Dist: pytest-cov==6.1.0; extra == "dev"
Requires-Dist: pytest-mypy-plugins==3.2.0; extra == "dev"
Requires-Dist: pyyaml==6.0.2; extra == "dev"
Requires-Dist: ruff==0.11.3; extra == "dev"
Requires-Dist: shellcheck-py==0.10.0.1; extra == "dev"
Requires-Dist: shfmt-py==3.11.0.2; extra == "dev"
Requires-Dist: sphinx-lint==1.0.0; extra == "dev"
Requires-Dist: tomli==2.2.1; extra == "dev"
Requires-Dist: vulture==2.14; extra == "dev"
Requires-Dist: yamlfix==1.17.0; extra == "dev"
Provides-Extra: release
Requires-Dist: check-wheel-contents==0.6.1; extra == "release"
Dynamic: license-file
